README.rst
setup.py
pyliterature/__init__.py
pyliterature/pyliterature.py
pyliterature.egg-info/PKG-INFO
pyliterature.egg-info/SOURCES.txt
pyliterature.egg-info/dependency_links.txt
pyliterature.egg-info/requires.txt
pyliterature.egg-info/top_level.txt