Metadata-Version: 1.0
Name: pyliterature
Version: 0.1.4
Summary: A Python web wrapper and text mining package for the scientific journal, including Nature, Science, ScienceDirect, Wiley, ACS publication, RSC publication and so on.
Home-page: https://github.com/superstar54/pyliterature
Author: Xing Wang
Author-email: xingwang1991@gmail.com
License: MIT License
Platform: any
